unhidden/__init__.py
unhidden/main.py
unhidden-0.6.0.dist-info/entry_points.txt
unhidden-0.6.0.dist-info/WHEEL
unhidden-0.6.0.dist-info/METADATA
unhidden-0.6.0.dist-info/RECORD
