Metadata-Version: 2.1
Name: unhidden
Version: 0.6.0
Summary: 
Author: Burak Akkaya
Author-email: akkaya.burak@outlook.com
Requires-Python: >=3.10,<4.0
Classifier: Programming Language :: Python :: 3
Classifier: Programming Language :: Python :: 3.10
Requires-Dist: pandas (>=1.5.0,<2.0.0)
Requires-Dist: requests (>=2.28.1,<3.0.0)
Requires-Dist: typer (>=0.6.1,<0.7.0)
